poster3/__init__.py
poster3/encode.py
poster3/streaminghttp.py
tests/__init__.py
tests/test_encode.py
tests/test_server.py
tests/test_streaming.py
poster3-0.8.1.dist-info/METADATA
poster3-0.8.1.dist-info/WHEEL
poster3-0.8.1.dist-info/top_level.txt
poster3-0.8.1.dist-info/zip-safe
poster3-0.8.1.dist-info/RECORD
