Metadata-Version: 2.1
Name: poster3
Version: 0.8.1
Summary: Streaming HTTP uploads and multipart/form-data encoding
Home-page: http://atlee.ca/software/poster
Author: Chris AtLee
Author-email: chris@atlee.ca
License: MIT
Download-URL: http://atlee.ca/software/poster/dist/0.8.1
Keywords: python http post multipart/form-data file upload
Platform: UNKNOWN
Classifier: Intended Audience :: Developers
Classifier: License :: OSI Approved :: MIT License
Classifier: Natural Language :: English
Classifier: Programming Language :: Python
Classifier: Topic :: Internet :: WWW/HTTP
Classifier: Topic :: Software Development :: Libraries :: Python Modules
Provides-Extra: poster3
Requires-Dist: buildutils ; extra == 'poster3'
Requires-Dist: sphinx ; extra == 'poster3'
